{
  "mappings": {
    "properties": {
      "timestamp": {"type": "date"},
      "action": {"type": "keyword"},
      "alias": {"type": "keyword"},
      "old_indices": {"type": "keyword"},
      "new_index": {"type": "keyword"},
      "counts": {
        "properties": {
          "source": {"type": "long"},
          "target": {"type": "long"}
        }
      },
      "model": {"type": "keyword"},
      "metrics": {"type": "object", "enabled": false},
      "git_commit": {"type": "keyword"}
    }
  }
}
